xia_framework/__init__.py
xia_framework/application.py
xia_framework/base.py
xia_framework/cosmos.py
xia_framework/foundation.py
xia_framework/realm.py
xia_framework/singularity.py
xia_framework/tools/__init__.py
xia_framework/tools/gcloud.py
xia_framework/tools/gh.py
xia_framework-0.0.66.dist-info/LICENSE
xia_framework-0.0.66.dist-info/METADATA
xia_framework-0.0.66.dist-info/WHEEL
xia_framework-0.0.66.dist-info/top_level.txt
xia_framework-0.0.66.dist-info/RECORD
