Metadata-Version: 2.1
Name: xia-framework
Version: 0.0.66
Summary: xia-framework
Requires-Python: >=3.9
License-File: LICENSE
Requires-Dist: PyYAML
Requires-Dist: ruamel.yaml
